{"name":"B站小黄脸","prefix":"bmoji_","type":"png","icon":"unavailble_doge","items":["unavailble_doge","hot","silme","mask","doge","bravo","ok","wow","not_open","onlooker","comical","grin","call","hei","naughty","bao_fu","crack_melon_seeds","smile_cry","tibetan_fox","blush","give_love","dudu","oh","heartbeat","lemon","wail","blushing","what","haha","smirking","hehe","titter","ah","um","insidious","jiong","stagnate","heihei","wa","cute","emm","good","applaud","um_2","oops","sad","hem","hurt","cold","ill","scared","spit","palming","shh","hmm","bye","roll_eye","sleeply","hard","cool","unhappy","grimace","aaa","angry","shui_dao","koi","fu","drumstick","snow","cheers","love","win","strong","thanks","please","thumb_up","hug_together","knees","my_fault","abandon"]}